{
  "containerimage.config.digest": "sha256:85b1b8dcdbe239c98341470c0f2e566007bcd260f6c15b3fdddb460345b6f22f",
  "containerimage.descriptor": {
    "mediaType": "application/vnd.docker.distribution.manifest.v2+json",
    "digest": "sha256:58a660882848dd948e102a9b729665a2c00da44011941cfc45f4a2da4671e719",
    "size": 703,
    "annotations": {
      "org.opencontainers.image.created": "2025-05-29T11:16:00Z"
    },
    "platform": {
      "architecture": "amd64",
      "os": "linux"
    }
  },
  "containerimage.digest": "sha256:58a660882848dd948e102a9b729665a2c00da44011941cfc45f4a2da4671e719",
  "image.name": "docker.io/library/keycrux:latest"
}